clickzetta_ingestion/__init__.py
clickzetta_ingestion/version.py
clickzetta_ingestion/_proto/__init__.py
clickzetta_ingestion/_proto/__init__.pyi
clickzetta_ingestion/_proto/account_pb2.py
clickzetta_ingestion/_proto/account_pb2.pyi
clickzetta_ingestion/_proto/account_pb2_grpc.py
clickzetta_ingestion/_proto/bit_set_pb2.py
clickzetta_ingestion/_proto/bit_set_pb2.pyi
clickzetta_ingestion/_proto/bit_set_pb2_grpc.py
clickzetta_ingestion/_proto/block_bloom_filter_pb2.py
clickzetta_ingestion/_proto/block_bloom_filter_pb2.pyi
clickzetta_ingestion/_proto/block_bloom_filter_pb2_grpc.py
clickzetta_ingestion/_proto/bucket_info_pb2.py
clickzetta_ingestion/_proto/bucket_info_pb2.pyi
clickzetta_ingestion/_proto/bucket_info_pb2_grpc.py
clickzetta_ingestion/_proto/compression_pb2.py
clickzetta_ingestion/_proto/compression_pb2.pyi
clickzetta_ingestion/_proto/compression_pb2_grpc.py
clickzetta_ingestion/_proto/connection_meta_pb2.py
clickzetta_ingestion/_proto/connection_meta_pb2.pyi
clickzetta_ingestion/_proto/connection_meta_pb2_grpc.py
clickzetta_ingestion/_proto/coordinator_service_pb2.py
clickzetta_ingestion/_proto/coordinator_service_pb2.pyi
clickzetta_ingestion/_proto/coordinator_service_pb2_grpc.py
clickzetta_ingestion/_proto/data_type_pb2.py
clickzetta_ingestion/_proto/data_type_pb2.pyi
clickzetta_ingestion/_proto/data_type_pb2_grpc.py
clickzetta_ingestion/_proto/ddl_pb2.py
clickzetta_ingestion/_proto/ddl_pb2.pyi
clickzetta_ingestion/_proto/ddl_pb2_grpc.py
clickzetta_ingestion/_proto/encryption_pb2.py
clickzetta_ingestion/_proto/encryption_pb2.pyi
clickzetta_ingestion/_proto/encryption_pb2_grpc.py
clickzetta_ingestion/_proto/expression_pb2.py
clickzetta_ingestion/_proto/expression_pb2.pyi
clickzetta_ingestion/_proto/expression_pb2_grpc.py
clickzetta_ingestion/_proto/file_format_type_pb2.py
clickzetta_ingestion/_proto/file_format_type_pb2.pyi
clickzetta_ingestion/_proto/file_format_type_pb2_grpc.py
clickzetta_ingestion/_proto/file_meta_data_pb2.py
clickzetta_ingestion_python_v2-0.8.105.dist-info/licenses/LICENSE
clickzetta_ingestion_python_v2-0.8.105.dist-info/METADATA
clickzetta_ingestion_python_v2-0.8.105.dist-info/WHEEL
clickzetta_ingestion_python_v2-0.8.105.dist-info/top_level.txt
clickzetta_ingestion_python_v2-0.8.105.dist-info/RECORD
